sqlalchemy_oceanbase/__init__.py
sqlalchemy_oceanbase/base.py
sqlalchemy_oceanbase/conftest.py
sqlalchemy_oceanbase/reflection.py
sqlalchemy_oceanbase-0.1.6.dist-info/LICENSE
sqlalchemy_oceanbase-0.1.6.dist-info/METADATA
sqlalchemy_oceanbase-0.1.6.dist-info/WHEEL
sqlalchemy_oceanbase-0.1.6.dist-info/entry_points.txt
sqlalchemy_oceanbase-0.1.6.dist-info/RECORD
