Metadata-Version: 2.3
Name: sqlalchemy-oceanbase
Version: 0.1.6
Summary: Sqlalchemy dialect for OceanBase mysql tenant
License: MIT
Author: John Lyu
Author-email: lvjunhong@citics.com
Requires-Python: >=3.8
Classifier: License :: OSI Approved :: MIT License
Classifier: Programming Language :: Python :: 3
Classifier: Programming Language :: Python :: 3.8
Classifier: Programming Language :: Python :: 3.9
Classifier: Programming Language :: Python :: 3.10
Classifier: Programming Language :: Python :: 3.11
Classifier: Programming Language :: Python :: 3.12
Classifier: Programming Language :: Python :: 3.13
Requires-Dist: pymysql (>=1.1.0)
Requires-Dist: sqlalchemy (>=2.0.29)
